setup.py
src/pytyp/__init__.py
src/pytyp/util.py
src/pytyp.egg-info/PKG-INFO
src/pytyp.egg-info/SOURCES.txt
src/pytyp.egg-info/dependency_links.txt
src/pytyp.egg-info/top_level.txt
src/pytyp/s11n/__init__.py
src/pytyp/s11n/base.py
src/pytyp/s11n/json.py
src/pytyp/s11n/yaml.py
src/pytyp/spec/__init__.py
src/pytyp/spec/abcs.py
src/pytyp/spec/check.py
src/pytyp/spec/dispatch.py
src/pytyp/spec/future.py
src/pytyp/spec/record.py